./.gitignore
./CHANGELOG.md
./CLAUDE.md
./CONTRIBUTING.md
./DEVELOPMENT.md
./LICENSE
./PKG-INFO
./README.md
./TROUBLESHOOTING.md
./claude_monitor.py
./init_dependency.py
./pyproject.toml
claude_usage_monitor-1.0.6.dist-info/METADATA
claude_usage_monitor-1.0.6.dist-info/WHEEL
claude_usage_monitor-1.0.6.dist-info/entry_points.txt
claude_usage_monitor-1.0.6.dist-info/licenses/LICENSE
claude_usage_monitor-1.0.6.dist-info/RECORD
