Metadata-Version: 2.4
Name: claude-usage-monitor
Version: 1.0.6
Summary: A real-time terminal monitoring tool for Claude AI token usage
Project-URL: Homepage, https://github.com/Maciek-roboblog/Claude-Code-Usage-Monitor
Project-URL: Repository, https://github.com/Maciek-roboblog/Claude-Code-Usage-Monitor.git
Project-URL: Issues, https://github.com/Maciek-roboblog/Claude-Code-Usage-Monitor/issues
Author-email: Maciek <maciek@roboblog.eu>
License-Expression: MIT
License-File: LICENSE
Keywords: ai,claude,monitoring,terminal,token,usage
Classifier: Development Status :: 5 - Production/Stable
Classifier: Environment :: Console
Classifier: Intended Audience :: Developers
Classifier: License :: OSI Approved :: MIT License
Classifier: Operating System :: OS Independent
Classifier: Programming Language :: Python :: 3
Classifier: Programming Language :: Python :: 3.7
Classifier: Programming Language :: Python :: 3.8
Classifier: Programming Language :: Python :: 3.9
Classifier: Programming Language :: Python :: 3.10
Classifier: Programming Language :: Python :: 3.11
Classifier: Programming Language :: Python :: 3.12
Classifier: Topic :: Software Development
Classifier: Topic :: System :: Monitoring
Requires-Python: >=3.7
Requires-Dist: pytz
Provides-Extra: dev
Requires-Dist: pre-commit>=2.20.0; (python_version < '3.8') and extra == 'dev'
Requires-Dist: pre-commit>=3.0.0; (python_version >= '3.8') and extra == 'dev'
Requires-Dist: ruff>=0.8.0; extra == 'dev'
